{
  "series": [
    {
      "id": 3,
      "name": "Brooklyn Nine-Nine",
      "status": "watching",
      "genre": "Comédia",
      "comments": ""
    },
    {
      "name": "",
      "status": "watched",
      "genre": "",
      "comments": "",
      "id": 6
    },
    {
      "name": "Atypical",
      "status": "watched",
      "genre": "Drama",
      "comments": "",
      "id": 7
    },
    {
      "id": 9,
      "name": "Santa Clarita Diet",
      "status": "toWatch",
      "genre": "Comédia",
      "comments": ""
    },
    {
      "name": "Anne with an E",
      "status": "toWatch",
      "genre": "Drama",
      "comments": "",
      "id": 10
    },
    {
      "id": 11,
      "name": "Vikings",
      "status": "watching",
      "genre": "Drama",
      "comments": ""
    },
    {
      "name": "Supergirl",
      "status": "watched",
      "genre": "Ação",
      "comments": "",
      "id": 13
    },
    {
      "name": "Hanna",
      "status": "watched",
      "genre": "Ação",
      "comments": "",
      "id": 14
    },
    {
      "name": "Slasher",
      "status": "toWatch",
      "genre": "Terror",
      "comments": "",
      "id": 15
    },
    {
      "id": 16,
      "name": "Z Nation",
      "status": "toWatch",
      "genre": "Terror",
      "comments": ""
    },
    {
      "id": 17,
      "name": "Channel Zero",
      "status": "toWatch",
      "genre": "Terror",
      "comments": ""
    },
    {
      "name": "The Purge",
      "status": "watching",
      "genre": "Terror",
      "comments": "",
      "id": 18
    },
    {
      "name": "Scream",
      "status": "watched",
      "genre": "Terror",
      "comments": "",
      "id": 19
    },
    {
      "name": "Fortitude",
      "status": "watched",
      "genre": "Terror",
      "comments": "",
      "id": 20
    },
    {
      "name": "Wynonna Earp",
      "status": "toWatch",
      "genre": "Terror",
      "comments": "",
      "id": 21
    },
    {
      "name": "Rick and Morty",
      "status": "watched",
      "genre": "Comédia",
      "comments": "",
      "id": 22
    },
    {
      "name": "Good Girls",
      "status": "watching",
      "genre": "Comédia",
      "comments": "",
      "id": 23
    },
    {
      "name": "Superstore",
      "status": "watched",
      "genre": "Comédia",
      "comments": "",
      "id": 24
    },
    {
      "name": "Black Mirror",
      "status": "watched",
      "genre": "Drama",
      "comments": "",
      "id": 25
    },
    {
      "name": "The Boys",
      "status": "watched",
      "genre": "Ação",
      "comments": "",
      "id": 26
    },
    {
      "function (req, res) {\n  res.send(newSeries);\n  console.log(newSeries);\n}": "",
      "id": 27
    },
    {
      "function (req, res) {\n  res.send(newSeries);\n  console.log(newSeries);\n}": "",
      "id": 28
    },
    {
      "name": "testeti",
      "status": "watched",
      "genre": "Comédia",
      "comments": "",
      "id": 29
    },
    {
      "name": "testeti",
      "status": "watched",
      "genre": "Comédia",
      "comments": "",
      "id": 30
    },
    {
      "name": "testeti",
      "status": "watched",
      "genre": "Comédia",
      "comments": "",
      "id": 31
    },
    {
      "name": "testeti",
      "status": "watched",
      "genre": "Comédia",
      "comments": "",
      "id": 32
    },
    {
      "name": "testeti",
      "status": "watched",
      "genre": "Comédia",
      "comments": "",
      "id": 33
    },
    {
      "name": "testeti",
      "status": "watched",
      "genre": "Comédia",
      "comments": "",
      "id": 34
    },
    {
      "name": "testeti",
      "status": "watched",
      "genre": "Comédia",
      "comments": "",
      "id": 35
    },
    {
      "name": "testeti",
      "status": "watched",
      "genre": "Comédia",
      "comments": "",
      "id": 36
    },
    {
      "name": "testeti",
      "status": "watched",
      "genre": "Comédia",
      "comments": "",
      "id": 37
    },
    {
      "name": "testeti",
      "status": "watched",
      "genre": "Comédia",
      "comments": "",
      "id": 38
    }
  ],
  "genres": [
    "Comédia",
    "Drama",
    "Ação",
    "Terror"
  ]
}
